Metadata-Version: 1.0
Name: price-wwp-homework-python-reboot-da
Version: 0.1
Summary: Homework_reboot_da
Home-page: UNKNOWN
Author: UNKNOWN
Author-email: klimkin.k.va@gmail.com
License: UNKNOWN
Platform: UNKNOWN
